CHANGELIST.rst
LICENSE
MANIFEST.in
README.rst
setup.py
unittests.py
bin/gsync
docs/images/gsync_authentication.jpg
gsync.egg-info/PKG-INFO
gsync.egg-info/SOURCES.txt
gsync.egg-info/dependency_links.txt
gsync.egg-info/requires.txt
gsync.egg-info/top_level.txt
libgsync/__init__.py
libgsync/bind.py
libgsync/crawler.py
libgsync/filter.py
libgsync/output.py
libgsync/drive/__init__.py
libgsync/drive/client_json.py
libgsync/drive/file.py
libgsync/drive/mimetypes.py
libgsync/options/__init__.py
libgsync/options/doc.py
libgsync/sync/__init__.py
libgsync/sync/file/__init__.py
libgsync/sync/file/factory.py
libgsync/sync/file/local/__init__.py
libgsync/sync/file/remote/__init__.py