Metadata-Version: 1.0
Name: gsync
Version: 0.1.13
Summary: GSync - RSync for Google Drive
Home-page: https://github.com/iwonbigbro/gsync
Author: Craig Phillips
Author-email: iwonbigbro@gmail.com
License: BSD License
Keywords: rsync gsync google-drive transfer copy files ftp
Platform: UNKNOWN
